aiohttp_traversal/__init__.py
aiohttp_traversal/abc.py
aiohttp_traversal/router.py
aiohttp_traversal/traversal.py
aiohttp_traversal/ext/__init__.py
aiohttp_traversal/ext/resources.py
aiohttp_traversal/ext/static.py
aiohttp_traversal/ext/views.py
aiohttp_traversal-0.11.0.dist-info/METADATA
aiohttp_traversal-0.11.0.dist-info/WHEEL
aiohttp_traversal-0.11.0.dist-info/top_level.txt
aiohttp_traversal-0.11.0.dist-info/RECORD
