Metadata-Version: 2.1
Name: aiohttp-traversal
Version: 0.11.0
Summary: Traversal based router for aiohttp.web
Home-page: https://github.com/zzzsochi/aiohttp_traversal
Author: Alexander Zelenyak
Author-email: zzz.sochi@gmail.com
License: BSD
Keywords: asyncio,aiohttp,traversal,pyramid
Platform: UNKNOWN
Classifier: License :: OSI Approved :: BSD License
Classifier: Operating System :: POSIX
Classifier: Programming Language :: Python :: 3.5
Classifier: Programming Language :: Python :: 3.6
Classifier: Programming Language :: Python :: 3.7
Classifier: Topic :: Internet :: WWW/HTTP
Requires-Dist: aiohttp (>=2.0)
Requires-Dist: resolver-deco
Requires-Dist: zope.dottedname
